mcp_openmetadata/__init__.py
mcp_openmetadata/utils.py
mcp_openmetadata/hosts/cursor.py
mcp_openmetadata/server/__init__.py
mcp_openmetadata/server/__main__.py
mcp_openmetadata/server/app.py
mcp_openmetadata/server/main.py
mcp_openmetadata/server/settings.py
mcp_openmetadata/server/tools/__init__.py
mcp_openmetadata/server/tools/search.py
mcp_openmetadata/server/tools/table.py
mcp_openmetadata-0.1.0.dist-info/METADATA
mcp_openmetadata-0.1.0.dist-info/WHEEL
mcp_openmetadata-0.1.0.dist-info/licenses/LICENSE
mcp_openmetadata-0.1.0.dist-info/RECORD
