Metadata-Version: 2.4
Name: mcp-openmetadata
Version: 0.1.0
Summary: MCP server providing OpenMetadata APIs
Project-URL: Homepage, https://github.com/pfldy2850/mcp-openmetadata
Project-URL: Repository, https://github.com/pfldy2850/mcp-openmetadata
Project-URL: Documentation, https://github.com/pfldy2850/mcp-openmetadata#readme
Project-URL: Bug Tracker, https://github.com/pfldy2850/mcp-openmetadata/issues
Author-email: Dongyong Lee <pfldy2850@gmail.com>
License: MIT
License-File: LICENSE
Keywords: fastmcp,integration,mcp,metadata,openmetadata
Requires-Python: >=3.10
Requires-Dist: fastmcp>=0.4.1
Requires-Dist: httpx>=0.28.1
Requires-Dist: pydantic-settings>=2.8.1
